woodAI/__init__.py
woodAI/__init__.pyi
woodAI/ai_chat.py
woodAI-1.0.5.dist-info/LICENSE.txt
woodAI-1.0.5.dist-info/METADATA
woodAI-1.0.5.dist-info/WHEEL
woodAI-1.0.5.dist-info/top_level.txt
woodAI-1.0.5.dist-info/RECORD
